pycrdfcli/__init__.py
pycrdfcli/pycrdfcli.py
pycrdfcli/requirements.txt
pycrdfcli-1.6.dist-info/METADATA
pycrdfcli-1.6.dist-info/WHEEL
pycrdfcli-1.6.dist-info/entry_points.txt
pycrdfcli-1.6.dist-info/top_level.txt
pycrdfcli-1.6.dist-info/RECORD
