Metadata-Version: 2.4
Name: pycrdfcli
Version: 1.6
Summary: A simple Python script to interact with CRDF (crdf.fr) APIs from CLI.
Author-email: tdebize@mail.com
License-Expression: LGPL-3.0-or-later
Project-URL: Homepage, https://github.com/maaaaz/pycrdfcli
Keywords: crdf,crdf.fr,cli,malware,phishing,threatcenter,threat,api
Classifier: Topic :: Security
Classifier: Programming Language :: Python :: 3
Requires-Python: >=3
Requires-Dist: requests[socks]
Requires-Dist: w3lib
Requires-Dist: validators
